{"info":{"_postman_id":"29327cea-8a3d-40e6-aad3-261debf6c754","name":"repo2Doc3","schema":"https://schema.getpostman.com/json/collection/v2.1.0/collection.json"},"item":[{"name":"Sample endpoint: Returns details about a particular user updated","id":"ff006cfa-2167-47d0-a435-6b5784f36b65","request":{"method":"GET","header":[],"url":{"raw":"{{baseUrl}}/user?id=-37204088","host":["{{baseUrl}}"],"path":["user"],"query":[{"key":"id","value":"-37204088","description":"(Required) ID of the user"}]}},"response":[{"id":"7441b038-33d5-47bb-98cc-0f7b9dc54a9b","name":"Sample response: Details about a user by ID","originalRequest":{"method":"GET","header":[],"url":{"raw":"{{baseUrl}}/user?id=-37204088","host":["{{baseUrl}}"],"path":["user"],"query":[{"key":"id","value":"-37204088"}]}},"status":"OK","code":200,"_postman_previewlanguage":"json","header":[{"disabled":false,"description":"A link to the next page of responses","key":"x-next","value":"dolor magn"},{"key":"Content-Type","value":"application/json"}],"cookie":[],"responseTime":null,"body":"{\n \"id\": 20317348,\n \"name\": \"eu es\",\n \"tag\": \"mollit et quis fugiat\"\n}"},{"id":"055fcb5e-78f2-43fe-903d-d4f0ec2c78e8","name":"Unexpected error","originalRequest":{"method":"GET","header":[],"url":{"raw":"{{baseUrl}}/user?id=-37204088","host":["{{baseUrl}}"],"path":["user"],"query":[{"key":"id","value":"-37204088"}]}},"status":"Internal Server Error","code":500,"_postman_previewlanguage":"json","header":[{"key":"Content-Type","value":"application/json"}],"cookie":[],"responseTime":null,"body":"{\n \"code\": -80422899,\n \"message\": \"amet\"\n}"}]}],"variable":[{"id":"c633f347-4a72-43d6-b3a6-eb0d87346992","key":"baseUrl","value":"http://localhost:3000","type":"string"}]}
